DecisionTreeConstraints/MDL.py
DecisionTreeConstraints/SizeConstraintPruning.py
DecisionTreeConstraints/__init__.py
DecisionTreeConstraints-0.1.dist-info/DESCRIPTION.rst
DecisionTreeConstraints-0.1.dist-info/METADATA
DecisionTreeConstraints-0.1.dist-info/RECORD
DecisionTreeConstraints-0.1.dist-info/WHEEL
DecisionTreeConstraints-0.1.dist-info/metadata.json
DecisionTreeConstraints-0.1.dist-info/top_level.txt
