Metadata-Version: 2.0
Name: DecisionTreeConstraints
Version: 0.1
Summary: Building Decision Trees with Constraints
Home-page: https://github.com/valiro21/DecisionTreeConstraints
Author: Valentin Rosca
Author-email: rosca.valentin2012@gmail.com
License: UNKNOWN
Keywords: decision trees classifier pruning constraints
Platform: UNKNOWN
Classifier: Development Status :: 3 - Alpha
Classifier: Programming Language :: Python :: 3
Classifier: License :: OSI Approved :: MIT License
Classifier: Operating System :: OS Independent
Classifier: Intended Audience :: Science/Research
Classifier: Intended Audience :: Developers
